COPYING
COPYING.LESSER
MANIFEST.in
README.rst
README_development.rst
setup.py
ha_JayDeBeApi.egg-info/PKG-INFO
ha_JayDeBeApi.egg-info/SOURCES.txt
ha_JayDeBeApi.egg-info/dependency_links.txt
ha_JayDeBeApi.egg-info/requires.txt
ha_JayDeBeApi.egg-info/top_level.txt
ha_jaydebeapi/__init__.py
test/test_integration.py
test/test_mock.py
test/testsuite.py