Metadata-Version: 1.1
Name: ha-JayDeBeApi
Version: 2.1.2
Summary: Use JDBC database drivers from Python 2/3 or Jython with a DB-API.
Home-page: https://github.com/anilpai/jaydebeapi
Author: Anil Pai
Author-email: apai@homeaway.com
License: GNU LGPL
Keywords: db api java jdbc bridge connect sql jpype jython
Platform: UNKNOWN
Classifier: Development Status :: 4 - Beta
Classifier: Intended Audience :: Developers
Classifier: License :: OSI Approved :: GNU Library or Lesser General Public License (LGPL)
Classifier: Programming Language :: Java
Classifier: Programming Language :: Python
Classifier: Programming Language :: Python :: 2
Classifier: Programming Language :: Python :: 3
Classifier: Topic :: Database
Classifier: Topic :: Software Development :: Libraries :: Java Libraries
Classifier: Topic :: Software Development :: Libraries :: Python Modules
